yafowil.widget.array-1.8-py3.9-nspkg.pth
yafowil/widget/array/__init__.py
yafowil/widget/array/example.py
yafowil/widget/array/tests.py
yafowil/widget/array/widget.py
yafowil/widget/array/resources/widget.js
yafowil/widget/array/resources/bootstrap/widget.css
yafowil/widget/array/resources/default/widget.css
yafowil/widget/array/resources/default/images/icon_add.png
yafowil/widget/array/resources/default/images/icon_down.png
yafowil/widget/array/resources/default/images/icon_down_disabled.png
yafowil/widget/array/resources/default/images/icon_remove.png
yafowil/widget/array/resources/default/images/icon_up.png
yafowil/widget/array/resources/default/images/icon_up_disabled.png
yafowil/widget/array/resources/plone5/widget.css
yafowil_widget_array-1.8.dist-info/licenses/LICENSE.rst
yafowil_widget_array-1.8.dist-info/METADATA
yafowil_widget_array-1.8.dist-info/WHEEL
yafowil_widget_array-1.8.dist-info/entry_points.txt
yafowil_widget_array-1.8.dist-info/namespace_packages.txt
yafowil_widget_array-1.8.dist-info/top_level.txt
yafowil_widget_array-1.8.dist-info/RECORD
